trx_icbc/__init__.py
trx_icbc/app.py
trx_icbc/carga_modelo_corto.py
trx_icbc/carga_modelo_largo.py
trx_icbc/cv.py
trx_icbc/data_prepro.py
trx_icbc/ingesta_prep.py
trx_icbc/iter_predict.py
trx_icbc/main.py
trx_icbc/monitoring_report.py
trx_icbc/predicciones.py
trx_icbc/scoring.py
trx_icbc-1.1.dist-info/METADATA
trx_icbc-1.1.dist-info/WHEEL
trx_icbc-1.1.dist-info/top_level.txt
trx_icbc-1.1.dist-info/RECORD
