Metadata-Version: 2.1
Name: trx-icbc
Version: 1.1
Summary: transaction prediction models for access and mobile channels
Home-page: UNKNOWN
Author: ['Tempelsman Joaquin, Miranda Chab']
Author-email: jtempelsman@icbc.com.ar
License: MIT
Platform: UNKNOWN
Requires-Dist: pandas
Requires-Dist: numpy
Requires-Dist: logging
Requires-Dist: datetime
Requires-Dist: typer
Requires-Dist: plotly
Requires-Dist: sphinx-rtd-theme
